atomic_agents/__init__.py
atomic_agents/agents/__init__.py
atomic_agents/agents/atomic_agent.py
atomic_agents/base/__init__.py
atomic_agents/base/base_io_schema.py
atomic_agents/base/base_prompt.py
atomic_agents/base/base_resource.py
atomic_agents/base/base_tool.py
atomic_agents/connectors/__init__.py
atomic_agents/connectors/mcp/__init__.py
atomic_agents/connectors/mcp/mcp_definition_service.py
atomic_agents/connectors/mcp/mcp_factory.py
atomic_agents/connectors/mcp/schema_transformer.py
atomic_agents/context/__init__.py
atomic_agents/context/chat_history.py
atomic_agents/context/system_prompt_generator.py
atomic_agents/utils/__init__.py
atomic_agents/utils/format_tool_message.py
atomic_agents/utils/token_counter.py
atomic_assembler/__init__.py
atomic_assembler/app.py
atomic_assembler/color_utils.py
atomic_assembler/constants.py
atomic_assembler/main.py
atomic_assembler/utils.py
atomic_assembler/screens/atomic_tool_explorer.py
atomic_assembler/screens/file_explorer.py
atomic_assembler/screens/main_menu.py
atomic_assembler/screens/tool_info_screen.py
atomic_assembler/widgets/confirmation_modal.py
atomic_assembler/widgets/generic_list.py
atomic_assembler/widgets/gradient_title.py
atomic_assembler/widgets/icon_selection_list.py
atomic_assembler/widgets/menu.py
atomic_assembler/widgets/new_item_input.py
atomic_assembler/widgets/tool_info_display.py
atomic_agents-2.5.0.dist-info/METADATA
atomic_agents-2.5.0.dist-info/WHEEL
atomic_agents-2.5.0.dist-info/entry_points.txt
atomic_agents-2.5.0.dist-info/licenses/LICENSE
atomic_agents-2.5.0.dist-info/RECORD
